mordecai3/__init__.py
mordecai3/elastic_utilities.py
mordecai3/error_analysis.py
mordecai3/error_utils.py
mordecai3/geoparse.py
mordecai3/mordecai_streamlit.py
mordecai3/mordecai_utilities.py
mordecai3/roberta_qa.py
mordecai3/torch_model.py
mordecai3/train.py
mordecai3/assets/countryInfo.txt
mordecai3/assets/country_bert_768.npy
mordecai3/assets/feature_code_dict.json
mordecai3/assets/hierarchy.txt
mordecai3/assets/mordecai_2023-03-28.pt
mordecai3/assets/wikipedia-iso-country-codes.txt
mordecai3-3.0.0a0.dist-info/METADATA
mordecai3-3.0.0a0.dist-info/WHEEL
mordecai3-3.0.0a0.dist-info/dependency_links.txt
mordecai3-3.0.0a0.dist-info/top_level.txt
mordecai3-3.0.0a0.dist-info/RECORD
