Metadata-Version: 2.1
Name: mordecai3
Version: 3.0.0a0
Home-page: http://github.com/ahalterman/mordecai3/
Author: Andy Halterman
Author-email: ahalterman0@gmail.com
License: MIT
Keywords: geoparsing,nlp,geocoding,toponym resolution
Requires-Dist: typer (<1.0,>=0.3.2)
Requires-Dist: spacy-transformers (<2.0,>=1.0.1)
Requires-Dist: transformers (<5.0,>=4.2.2)
Requires-Dist: spacy (<4.0,>=3.5)
Requires-Dist: torch (<2.0,>=1.2.0)
Requires-Dist: elasticsearch (<8.0,>=7.11.0)
Requires-Dist: elasticsearch-dsl (<8.0,>=7.3.0)
Requires-Dist: scikit-learn (>=0.24.1)
Requires-Dist: pandas (<2.0,>=1.2.2)
Requires-Dist: jellyfish (<2.0,>=0.8.2)
Requires-Dist: tqdm (<5.0,>=4.56.1)
Requires-Dist: numpy (<2.0,>=1.19.5)
Requires-Dist: jsonlines (<4.0,>=3.0.0)
Requires-Dist: xmltodict (<1.0,>=0.12.0)
